ilorest/__init__.py
ilorest/cliutils.py
ilorest/debug_utils.py
ilorest/logging_config_path.py
ilorest/rdmc.py
ilorest/rdmc_base_classes.py
ilorest/rdmc_helper.py
ilorest/security_masking.py
ilorest/versioning.py
ilorest/chiflibrary/__init__.py
ilorest/chiflibrary/ilorest_chif.dll
ilorest/chiflibrary/ilorest_chif.so
ilorest/chiflibrary/arm/__init__.py
ilorest/chiflibrary/arm/ilorest_chif.so
ilorest/config/__init__.py
ilorest/config/config.py
ilorest/config/rdmc_config.py
ilorest/extensions/__init__.py
ilorest/extensions/BIOS_COMMANDS/BiosDefaultsCommand.py
ilorest/extensions/BIOS_COMMANDS/BootOrderCommand.py
ilorest/extensions/BIOS_COMMANDS/IscsiConfigCommand.py
ilorest/extensions/BIOS_COMMANDS/SetPasswordCommand.py
ilorest/extensions/BIOS_COMMANDS/__init__.py
ilorest/extensions/COMMANDS/CommitCommand.py
ilorest/extensions/COMMANDS/DetectiLOCommand.py
ilorest/extensions/COMMANDS/GetCommand.py
ilorest/extensions/COMMANDS/InfoCommand.py
ilorest/extensions/COMMANDS/ListCommand.py
ilorest/extensions/COMMANDS/LoadCommand.py
ilorest/extensions/COMMANDS/LoginCommand.py
ilorest/extensions/COMMANDS/LogoutCommand.py
ilorest/extensions/COMMANDS/PendingChangesCommand.py
ilorest/extensions/COMMANDS/ResultsCommand.py
ilorest/extensions/COMMANDS/SaveCommand.py
ilorest/extensions/COMMANDS/SelectCommand.py
ilorest/extensions/COMMANDS/SetCommand.py
ilorest/extensions/COMMANDS/StatusCommand.py
ilorest/extensions/COMMANDS/TypesCommand.py
ilorest/extensions/COMMANDS/__init__.py
ilorest/extensions/COMMANDS/REQUIREDCOMMANDS/ExitCommand.py
ilorest/extensions/COMMANDS/REQUIREDCOMMANDS/HelpCommand.py
ilorest/extensions/COMMANDS/REQUIREDCOMMANDS/__init__.py
ilorest/extensions/PERSISTENT_MEMORY_COMMANDS/AdvancedPmmConfigCommand.py
ilorest/extensions/PERSISTENT_MEMORY_COMMANDS/ApplyPmemConfigCommand.py
ilorest/extensions/PERSISTENT_MEMORY_COMMANDS/ClearPendingConfigCommand.py
ilorest/extensions/PERSISTENT_MEMORY_COMMANDS/DisplaySecurityStateCommand.py
ilorest-7.0.0.0.dist-info/METADATA
ilorest-7.0.0.0.dist-info/WHEEL
ilorest-7.0.0.0.dist-info/entry_points.txt
ilorest-7.0.0.0.dist-info/top_level.txt
ilorest-7.0.0.0.dist-info/RECORD
